{"focus":{"id":"H05317","slug":"maud-mazeine-1881","n":"Maud Hooker Brown Mazeine","by":1881,"dy":1953,"sx":"u","hd":true,"td":false,"ee":false,"g":10},"spouses":[{"order":1,"spouse":{"id":"I01354","slug":"raymond-mazeine-1878","n":"Raymond Mazeine","by":1878,"dy":1950,"sx":"u","hd":false,"td":false,"ee":false,"g":0},"year":1906,"children":[]}],"parents":{"father":{"id":"I01353","slug":"george-brown-1847","n":"George Selah Brown","by":1847,"dy":1919,"sx":"u","hd":false,"td":false,"ee":false,"g":0},"mother":{"id":"H04418","slug":"florence-brown-1852","n":"Florence Rosella Graham Brown","by":1852,"dy":1924,"sx":"u","hd":true,"td":false,"ee":false,"g":9}},"grandparents":{"paternal":{},"maternal":{"father":{"id":"I01352","slug":"franklin-graham-1825","n":"Franklin Graham","by":1825,"dy":1897,"sx":"u","hd":false,"td":false,"ee":false,"g":0},"mother":{"id":"H02839","slug":"mary-graham-1827","n":"Mary Elizabeth Atwood Graham","by":1827,"dy":1902,"sx":"u","hd":true,"td":false,"ee":false,"g":8}}},"grandchildren":[],"siblings_count":0}