{"focus":{"id":"HD0212","slug":"horace-burwell-1813","n":"Horace B Burwell","by":1813,"dy":1849,"sx":"m","hd":true,"td":false,"ee":false,"g":8},"spouses":[{"order":1,"spouse":{"id":"X01101","slug":"mary-beach","n":"Mary Juliana Beach","by":null,"dy":null,"sx":"f","hd":false,"td":false,"ee":false,"g":null},"year":1839,"children":[{"id":"HD0497","slug":"amelia-burwell","n":"Amelia V Burwell","by":null,"dy":1844,"sx":"u","hd":true,"td":false,"ee":false,"g":9},{"id":"HD0498","slug":"emma-burwell-1844","n":"Emma E Burwell","by":1844,"dy":1880,"sx":"f","hd":true,"td":false,"ee":false,"g":9},{"id":"HD0499","slug":"ellen-burwell-1845","n":"Ellen F Burwell","by":1845,"dy":1864,"sx":"u","hd":true,"td":false,"ee":false,"g":9},{"id":"HD0500","slug":"marion-burwell-1848","n":"Marion A Burwell","by":1848,"dy":1850,"sx":"f","hd":true,"td":false,"ee":false,"g":9},{"id":"HD0501","slug":"horace-burwell-1849","n":"Horace Beach Burwell","by":1849,"dy":1922,"sx":"m","hd":true,"td":false,"ee":false,"g":9}]}],"parents":{"father":{"id":"HD0209","slug":"thomas-burwell-1790","n":"Thomas Burwell","by":1790,"dy":1881,"sx":"m","hd":true,"td":false,"ee":false,"g":7},"mother":{"id":"I00095","slug":"sarah-beach-1799","n":"Sarah Beach Burwell","by":1799,"dy":1888,"sx":"f","hd":false,"td":false,"ee":false,"g":null}},"grandparents":{"paternal":{"father":{"id":"HD0202","slug":"john-burwell-1750","n":"John Burwell","by":1750,"dy":1830,"sx":"m","hd":true,"td":false,"ee":false,"g":6},"mother":{"id":"I00094","slug":"mary-welch-1751","n":"Mary Welch Burwell","by":1751,"dy":1809,"sx":"f","hd":false,"td":false,"ee":false,"g":null}},"maternal":{}},"grandchildren":[],"siblings_count":6}