{"focus":{"id":"HD3698","slug":"charles-cowles-1857","n":"Charles Sumner Cowles","by":1857,"dy":null,"sx":"u","hd":true,"td":false,"ee":false,"g":9},"spouses":[],"parents":{"father":{"id":"HD3684","slug":"alfred-cowles-ii-1826","n":"Alfred Cowles (II)","by":1826,"dy":1914,"sx":"u","hd":true,"td":false,"ee":false,"g":8},"mother":{"id":"I00390","slug":"harriet-hill-1832","n":"Harriet M. Hill Tourtelotte Cowles","by":1832,"dy":1908,"sx":"u","hd":false,"td":false,"ee":false,"g":null}},"grandparents":{"paternal":{"father":{"id":"H01138","slug":"egbert-cowles-1785","n":"Egbert Cowles","by":1785,"dy":1885,"sx":"u","hd":true,"td":false,"ee":false,"g":7},"mother":{"id":"I00383","slug":"sophia-woodruff-1789","n":"Sophia Sarah Woodruff Cowles","by":1789,"dy":1874,"sx":"u","hd":false,"td":false,"ee":false,"g":null}},"maternal":{}},"grandchildren":[],"siblings_count":2}