{"focus":{"id":"HD6007","slug":"fritz-a-greve-1902","n":"Fritz A. Greve","by":1902,"dy":1966,"sx":"m","hd":true,"td":false,"ee":false,"g":10},"spouses":[],"parents":{"father":{"id":"I01623","slug":"adolph-emil-august-greve-1877","n":"Adolph Emil August Greve","by":1877,"dy":1952,"sx":"m","hd":false,"td":false,"ee":false,"g":null},"mother":{"id":"HD5999","slug":"muriel-zerlina-burr-1884","n":"Muriel Zerlina Burr Greve","by":1884,"dy":1958,"sx":"m","hd":true,"td":false,"ee":false,"g":9}},"grandparents":{"paternal":{},"maternal":{"father":{"id":"HD5993","slug":"aaron-burr-1836","n":"Aaron Burr","by":1836,"dy":1903,"sx":"m","hd":true,"td":false,"ee":false,"g":8},"mother":{"id":"I01619","slug":"electa-orinda-austin-1841","n":"Electa Orinda Austin Burr","by":1841,"dy":1913,"sx":"m","hd":false,"td":false,"ee":false,"g":null}}},"grandchildren":[],"siblings_count":7}