{"focus":{"id":"I00327","slug":"john-cecil-jr-1923","n":"John Howe Cecil Jr.","by":1923,"dy":2024,"sx":"m","hd":false,"td":false,"ee":false,"g":null},"spouses":[{"order":1,"spouse":{"id":"HD2158","slug":"suzan-cecil-1929","n":"Suzan Whitney Knight Cecil","by":1929,"dy":2022,"sx":"f","hd":true,"td":false,"ee":false,"g":10},"year":1953,"children":[{"id":"HD3381","slug":"graham-cecil","n":"Graham Howe Cecil","by":null,"dy":null,"sx":"m","hd":true,"td":false,"ee":false,"g":11},{"id":"HD3382","slug":"sallie-stillwell","n":"Sallie Cecil Stillwell","by":null,"dy":null,"sx":"f","hd":true,"td":false,"ee":false,"g":11},{"id":"HD3383","slug":"maria-cecil","n":"Maria Whitney Cecil","by":null,"dy":null,"sx":"f","hd":true,"td":false,"ee":false,"g":11}]}],"parents":{},"grandparents":{"paternal":{},"maternal":{}},"grandchildren":[],"siblings_count":0}