{"focus":{"id":"I01805","slug":"carlene-curtis-1872","n":"Carlene Curtis Blunt","by":1872,"dy":1959,"sx":"u","hd":false,"td":false,"ee":false,"g":null},"spouses":[{"order":1,"spouse":{"id":"HD6510","slug":"john-ellsworth-blunt-1870","n":"II John Ellsworth Blunt","by":1870,"dy":1965,"sx":"u","hd":true,"td":false,"ee":false,"g":9},"year":1897,"children":[{"id":"HD6513","slug":"curtis-ellsworth-blunt-1899","n":"Curtis Ellsworth Blunt","by":1899,"dy":1962,"sx":"u","hd":true,"td":false,"ee":false,"g":10},{"id":"HD6514","slug":"john-ellsworth-blunt-1900","n":"III John Ellsworth Blunt","by":1900,"dy":1965,"sx":"u","hd":true,"td":false,"ee":false,"g":10},{"id":"HD6515","slug":"carleton-blunt-1905","n":"Carleton Blunt","by":1905,"dy":1988,"sx":"u","hd":true,"td":false,"ee":false,"g":10}]}],"parents":{},"grandparents":{"paternal":{},"maternal":{}},"grandchildren":[{"id":"HD6516","slug":"estelle-king-1930","n":"Estelle Blunt King","by":1930,"dy":2019,"sx":"u","hd":true,"td":false,"ee":false,"g":11,"via_parent_id":"HD6514"},{"id":"HD6517","slug":"john-thorp-blunt-1936","n":"John Thorp Blunt","by":1936,"dy":2020,"sx":"u","hd":true,"td":false,"ee":false,"g":11,"via_parent_id":"HD6514"}],"siblings_count":0}