{"focus":{"id":"X00611","slug":"george-coit-jr-1821","n":"George Coit Jr.","by":1821,"dy":1881,"sx":"m","hd":false,"td":false,"ee":false,"g":null},"spouses":[{"order":1,"spouse":{"id":"HD1894","slug":"catherine-coit-1829","n":"Catherine S Ketchum Coit","by":1829,"dy":1915,"sx":"f","hd":true,"td":false,"ee":false,"g":8},"year":1854,"children":[{"id":"HD1897","slug":"kate-coit-1857","n":"Kate Coit","by":1857,"dy":null,"sx":"f","hd":true,"td":false,"ee":false,"g":9},{"id":"HD1898","slug":"william-coit-1860","n":"William K Coit","by":1860,"dy":1891,"sx":"m","hd":true,"td":false,"ee":false,"g":9},{"id":"HD1899","slug":"sarah-coit-1865","n":"Sarah E Coit","by":1865,"dy":1949,"sx":"f","hd":true,"td":false,"ee":false,"g":9}]}],"parents":{},"grandparents":{"paternal":{},"maternal":{}},"grandchildren":[],"siblings_count":0}