{"person":{"id":"X01496","has_descendants_documented":false,"classification":{"include_in_path_calculation":false,"descent_from_thomas_hooker":false,"descent_from_john_talcott":false,"is_thomas_descendant":false,"is_talcott_descendant":false,"is_easter_egg":false},"tags":[],"sources":[],"gender":"female","number_of_marriages":1,"marriages":[{"marriage_number":1,"spouse_id":"HD1508","children_ids":[]}],"parents":{},"notable":{"is_notable":false,"notable_category":[]},"birth":{},"death":{},"cross_connections":[],"bio":{"display_name":"Edson D","first_name":"Edson","maiden_name":"D","married_names":[]},"residence":{},"baptism":{},"research_tags":[],"research_sources":[],"documents":[],"naming_inspiration":[],"institutions":[],"landmarks":[],"artworks":[],"quotes":[],"military_service":[],"slug":"edson-d"},"neighborhood":{"focus":{"id":"X01496","slug":"edson-d","n":"Edson D","by":null,"dy":null,"sx":"f","hd":false,"td":false,"ee":false,"g":null},"spouses":[{"order":1,"spouse":{"id":"HD1508","slug":"charles-brockett-1803","n":"Charles Brockett","by":1803,"dy":1884,"sx":"m","hd":true,"td":false,"ee":false,"g":7},"year":null,"children":[]}],"parents":{},"grandparents":{"paternal":{},"maternal":{}},"grandchildren":[],"siblings_count":0},"context":{"X01496":{"id":"X01496","has_descendants_documented":false,"classification":{"include_in_path_calculation":false,"descent_from_thomas_hooker":false,"descent_from_john_talcott":false,"is_thomas_descendant":false,"is_talcott_descendant":false,"is_easter_egg":false},"tags":[],"sources":[],"gender":"female","number_of_marriages":1,"marriages":[{"marriage_number":1,"spouse_id":"HD1508","children_ids":[]}],"parents":{},"notable":{"is_notable":false,"notable_category":[]},"birth":{},"death":{},"cross_connections":[],"bio":{"display_name":"Edson D","first_name":"Edson","maiden_name":"D","married_names":[]},"residence":{},"baptism":{},"research_tags":[],"research_sources":[],"documents":[],"naming_inspiration":[],"institutions":[],"landmarks":[],"artworks":[],"quotes":[],"military_service":[],"slug":"edson-d"},"HD1508":{"id":"HD1508","has_descendants_documented":true,"classification":{"include_in_path_calculation":true,"generation_from_thomas":7,"descent_from_thomas_hooker":true,"descent_from_john_talcott":false,"is_thomas_descendant":true,"is_talcott_descendant":false,"is_easter_egg":false},"parents":{"father_id":"H00886","mother_id":"X00484"},"tags":[],"sources":[{"short":"Online vital records / primary documents"}],"birth":{"year":1803},"death":{"year":1884},"gender":"male","marriages":[{"spouse_id":"X01496","children_ids":[],"marriage_number":1}],"number_of_marriages":1,"notable":{"is_notable":false,"notable_category":[]},"cross_connections":[],"bio":{"display_name":"Charles Brockett","first_name":"Charles","last_name":"Brockett","married_names":[]},"residence":{},"baptism":{},"research_tags":[],"research_sources":[],"documents":[],"naming_inspiration":[],"institutions":[],"landmarks":[],"artworks":[],"quotes":[],"military_service":[],"slug":"charles-brockett-1803"}},"burialCemetery":null,"institutionsById":{},"crossConnections":[]}