{"person":{"id":"X00702","has_descendants_documented":false,"classification":{"include_in_path_calculation":false,"descent_from_thomas_hooker":false,"descent_from_john_talcott":false,"is_thomas_descendant":false,"is_talcott_descendant":false,"is_easter_egg":false},"tags":[],"sources":[],"birth":{"year":1856,"month":3,"day":24,"city":"West Cornwall","state":"Connecticut"},"death":{"year":1919,"month":7,"day":1,"city":"Schenectady","state":"New York"},"gender":"male","number_of_marriages":1,"marriages":[{"marriage_number":1,"spouse_id":"HD2225","date_year":1888,"date_month":1,"date_day":19,"location_city":"Iron Mountain","location_state":"Michigan","children_ids":["HD2228","HD2229","HD2230","HD2231"]}],"parents":{},"notable":{"is_notable":false,"notable_category":[]},"cross_connections":[],"bio":{"display_name":"Edward Everett Brewster","first_name":"Edward","last_name":"Brewster","middle_name":"Everett","married_names":[]},"residence":{},"baptism":{},"research_tags":[],"research_sources":[],"documents":[],"naming_inspiration":[],"institutions":[],"landmarks":[],"artworks":[],"quotes":[],"military_service":[],"slug":"edward-brewster-1856"},"neighborhood":{"focus":{"id":"X00702","slug":"edward-brewster-1856","n":"Edward Everett Brewster","by":1856,"dy":1919,"sx":"m","hd":false,"td":false,"ee":false,"g":null},"spouses":[{"order":1,"spouse":{"id":"HD2225","slug":"elizabeth-edwards-1863","n":"Elizabeth Taylor Edwards","by":1863,"dy":1944,"sx":"f","hd":true,"td":false,"ee":false,"g":9},"year":1888,"children":[{"id":"HD2228","slug":"william-brewster-1889","n":"William Edwards Brewster","by":1889,"dy":1949,"sx":"m","hd":true,"td":false,"ee":false,"g":10},{"id":"HD2229","slug":"edwards-brewster-1893","n":"Edwards Pierpont Brewster","by":1893,"dy":1964,"sx":"m","hd":true,"td":false,"ee":false,"g":10},{"id":"HD2230","slug":"margaret-brewster-1894","n":"Margaret Harmon Brewster","by":1894,"dy":1970,"sx":"f","hd":true,"td":false,"ee":false,"g":10},{"id":"HD2231","slug":"frances-brewster-1896","n":"Frances Brewster","by":1896,"dy":1978,"sx":"f","hd":true,"td":false,"ee":false,"g":10}]}],"parents":{},"grandparents":{"paternal":{},"maternal":{}},"grandchildren":[],"siblings_count":0},"context":{"X00702":{"id":"X00702","has_descendants_documented":false,"classification":{"include_in_path_calculation":false,"descent_from_thomas_hooker":false,"descent_from_john_talcott":false,"is_thomas_descendant":false,"is_talcott_descendant":false,"is_easter_egg":false},"tags":[],"sources":[],"birth":{"year":1856,"month":3,"day":24,"city":"West Cornwall","state":"Connecticut"},"death":{"year":1919,"month":7,"day":1,"city":"Schenectady","state":"New York"},"gender":"male","number_of_marriages":1,"marriages":[{"marriage_number":1,"spouse_id":"HD2225","date_year":1888,"date_month":1,"date_day":19,"location_city":"Iron Mountain","location_state":"Michigan","children_ids":["HD2228","HD2229","HD2230","HD2231"]}],"parents":{},"notable":{"is_notable":false,"notable_category":[]},"cross_connections":[],"bio":{"display_name":"Edward Everett Brewster","first_name":"Edward","last_name":"Brewster","middle_name":"Everett","married_names":[]},"residence":{},"baptism":{},"research_tags":[],"research_sources":[],"documents":[],"naming_inspiration":[],"institutions":[],"landmarks":[],"artworks":[],"quotes":[],"military_service":[],"slug":"edward-brewster-1856"},"HD2225":{"id":"HD2225","has_descendants_documented":true,"classification":{"include_in_path_calculation":true,"generation_from_thomas":9,"descent_from_thomas_hooker":true,"descent_from_john_talcott":false,"is_thomas_descendant":true,"is_talcott_descendant":false,"is_easter_egg":false},"parents":{"father_id":"HD2183","mother_id":"X00701"},"tags":[],"sources":[],"birth":{"year":1863,"month":5,"day":14,"city":"Youngstown","state":"Ohio"},"death":{"year":1944,"month":7,"day":24},"marriages":[{"spouse_id":"X00702","children_ids":["HD2228","HD2229","HD2230","HD2231"],"marriage_number":1,"date_year":1888,"date_month":1,"date_day":19,"location_city":"Iron Mountain","location_state":"Michigan"}],"gender":"female","number_of_marriages":1,"notable":{"is_notable":false,"notable_category":[]},"cross_connections":[],"bio":{"display_name":"Elizabeth Taylor Edwards","first_name":"Elizabeth","middle_name":"Taylor","maiden_name":"Edwards","married_names":[]},"residence":{},"baptism":{},"research_tags":[],"research_sources":[],"documents":[],"naming_inspiration":[],"institutions":[],"landmarks":[],"artworks":[],"quotes":[],"military_service":[],"slug":"elizabeth-edwards-1863"},"HD2228":{"id":"HD2228","has_descendants_documented":false,"classification":{"include_in_path_calculation":false,"generation_from_thomas":10,"descent_from_thomas_hooker":true,"descent_from_john_talcott":false,"is_thomas_descendant":true,"is_talcott_descendant":false,"is_easter_egg":false},"parents":{"father_id":"X00702","mother_id":"HD2225"},"tags":[],"sources":[],"birth":{"year":1889,"month":6,"day":14,"city":"Iron Mountain","state":"Michigan"},"death":{"year":1949,"month":12,"day":14,"city":"Chicago","state":"Illinois"},"gender":"male","marriages":[],"notable":{"is_notable":false,"notable_category":[]},"cross_connections":[],"bio":{"display_name":"William Edwards Brewster","first_name":"William","last_name":"Brewster","middle_name":"Edwards","married_names":[]},"residence":{},"baptism":{},"research_tags":[],"research_sources":[],"documents":[],"naming_inspiration":[],"institutions":[],"landmarks":[],"artworks":[],"quotes":[],"military_service":[],"slug":"william-brewster-1889"},"HD2229":{"id":"HD2229","has_descendants_documented":false,"classification":{"include_in_path_calculation":false,"generation_from_thomas":10,"descent_from_thomas_hooker":true,"descent_from_john_talcott":false,"is_thomas_descendant":true,"is_talcott_descendant":false,"is_easter_egg":false},"parents":{"father_id":"X00702","mother_id":"HD2225"},"tags":[],"sources":[],"birth":{"year":1893,"month":2,"day":12,"city":"Iron Mountain","state":"Michigan"},"death":{"year":1964,"month":11,"day":23,"city":"Charleston","state":"South Carolina"},"gender":"male","marriages":[{"spouse_id":"X01550","children_ids":[],"marriage_number":1}],"number_of_marriages":1,"notable":{"is_notable":false,"notable_category":[]},"cross_connections":[],"bio":{"display_name":"Edwards Pierpont Brewster","first_name":"Edwards","last_name":"Brewster","middle_name":"Pierpont","married_names":[]},"residence":{},"baptism":{},"research_tags":[],"research_sources":[],"documents":[],"naming_inspiration":[],"institutions":[],"landmarks":[],"artworks":[],"quotes":[],"military_service":[],"slug":"edwards-brewster-1893"},"X01550":{"id":"X01550","has_descendants_documented":false,"classification":{"include_in_path_calculation":false,"descent_from_thomas_hooker":false,"descent_from_john_talcott":false,"is_thomas_descendant":false,"is_talcott_descendant":false,"is_easter_egg":false},"tags":[],"sources":[],"gender":"female","number_of_marriages":1,"marriages":[{"marriage_number":1,"spouse_id":"HD2229","children_ids":[]}],"parents":{},"notable":{"is_notable":false,"notable_category":[]},"birth":{},"death":{},"cross_connections":[],"bio":{"display_name":"Gertrude May Peene","first_name":"Gertrude","middle_name":"May","maiden_name":"Peene","married_names":[]},"residence":{},"baptism":{},"research_tags":[],"research_sources":[],"documents":[],"naming_inspiration":[],"institutions":[],"landmarks":[],"artworks":[],"quotes":[],"military_service":[],"slug":"gertrude-peene"},"HD2230":{"id":"HD2230","has_descendants_documented":false,"classification":{"include_in_path_calculation":false,"generation_from_thomas":10,"descent_from_thomas_hooker":true,"descent_from_john_talcott":false,"is_thomas_descendant":true,"is_talcott_descendant":false,"is_easter_egg":false},"parents":{"father_id":"X00702","mother_id":"HD2225"},"tags":[],"sources":[],"birth":{"year":1894,"month":9,"day":10},"death":{"year":1970,"month":4,"day":4},"gender":"female","marriages":[],"notable":{"is_notable":false,"notable_category":[]},"cross_connections":[],"bio":{"display_name":"Margaret Harmon Brewster","first_name":"Margaret","middle_name":"Harmon","maiden_name":"Brewster","married_names":[]},"residence":{},"baptism":{},"research_tags":[],"research_sources":[],"documents":[],"naming_inspiration":[],"institutions":[],"landmarks":[],"artworks":[],"quotes":[],"military_service":[],"slug":"margaret-brewster-1894"},"HD2231":{"id":"HD2231","has_descendants_documented":false,"classification":{"include_in_path_calculation":false,"generation_from_thomas":10,"descent_from_thomas_hooker":true,"descent_from_john_talcott":false,"is_thomas_descendant":true,"is_talcott_descendant":false,"is_easter_egg":false},"parents":{"father_id":"X00702","mother_id":"HD2225"},"tags":[],"sources":[],"birth":{"year":1896,"month":5,"day":9},"death":{"year":1978,"month":10,"day":17},"gender":"female","marriages":[],"notable":{"is_notable":false,"notable_category":[]},"cross_connections":[],"bio":{"display_name":"Frances Brewster","first_name":"Frances","maiden_name":"Brewster","married_names":[]},"residence":{},"baptism":{},"research_tags":[],"research_sources":[],"documents":[],"naming_inspiration":[],"institutions":[],"landmarks":[],"artworks":[],"quotes":[],"military_service":[],"slug":"frances-brewster-1896"}},"burialCemetery":null,"institutionsById":{},"crossConnections":[]}