{"person":{"id":"I01628","former_ids":[],"is_placeholder":false,"has_descendants_documented":false,"gender":"male","classification":{"is_thomas_descendant":false,"is_talcott_descendant":false,"is_thomas_spouse":false,"include_in_path_calculation":false,"is_easter_egg":false},"notable":{"is_notable":false,"notable_category":[]},"parents":{},"number_of_marriages":1,"marriages":[{"spouse_id":"HD6030","children_ids":["HD6031"],"marriage_number":1}],"tags":[],"narrative_blocks":[],"sources":[],"institutions":[],"landmarks":[],"artworks":[],"research_tags":[],"cross_connections":[],"quotes":[],"research_sources":[],"documents":[],"statues":[],"bio":{"first_name":"Elizabeth Crichton","last_name":"Battelle","display_name":"Elizabeth Crichton \"Bessie\" Battelle Vanderpoel","gender":"female","married_names":["Vanderpoel"],"maiden_name":"Battelle","photo_url":"https://res.cloudinary.com/dc5clrqtw/image/upload/v1780932970/174254825_29121f25-ddd2-4609-ad16-2c46503f9bee_ugpmuu.jpg"},"military_service":[],"career":[],"birth":{"year":1862,"country":"United States"},"death":{"year":1957,"country":"United States"},"burial":{},"education":[],"slug":"elizabeth-crichton-battelle-1862"},"neighborhood":{"focus":{"id":"I01628","slug":"elizabeth-crichton-battelle-1862","n":"Elizabeth Crichton \"Bessie\" Battelle Vanderpoel","by":1862,"dy":1957,"sx":"m","hd":false,"td":false,"ee":false,"g":null},"spouses":[{"order":1,"spouse":{"id":"HD6030","slug":"john-arent-vanderpoel-1866","n":"John Arent Vanderpoel","by":1866,"dy":1901,"sx":"m","hd":true,"td":false,"ee":false,"g":10},"year":null,"children":[{"id":"HD6031","slug":"floyd-lewis-vanderpoel-1891","n":"Floyd Lewis Vanderpoel","by":1891,"dy":1948,"sx":"m","hd":true,"td":false,"ee":false,"g":11}]}],"parents":{},"grandparents":{"paternal":{},"maternal":{}},"grandchildren":[{"id":"HD6032","slug":"john-arent-vanderpoel-1918","n":"John Arent Vanderpoel","by":1918,"dy":2008,"sx":"m","hd":true,"td":false,"ee":false,"g":12,"via_parent_id":"HD6031"},{"id":"HD6033","slug":"eric-vanderpoel-1921","n":"Eric Vanderpoel","by":1921,"dy":1940,"sx":"m","hd":true,"td":false,"ee":false,"g":12,"via_parent_id":"HD6031"}],"siblings_count":0},"context":{"I01628":{"id":"I01628","former_ids":[],"is_placeholder":false,"has_descendants_documented":false,"gender":"male","classification":{"is_thomas_descendant":false,"is_talcott_descendant":false,"is_thomas_spouse":false,"include_in_path_calculation":false,"is_easter_egg":false},"notable":{"is_notable":false,"notable_category":[]},"parents":{},"number_of_marriages":1,"marriages":[{"spouse_id":"HD6030","children_ids":["HD6031"],"marriage_number":1}],"tags":[],"narrative_blocks":[],"sources":[],"institutions":[],"landmarks":[],"artworks":[],"research_tags":[],"cross_connections":[],"quotes":[],"research_sources":[],"documents":[],"statues":[],"bio":{"first_name":"Elizabeth Crichton","last_name":"Battelle","display_name":"Elizabeth Crichton \"Bessie\" Battelle Vanderpoel","gender":"female","married_names":["Vanderpoel"],"maiden_name":"Battelle","photo_url":"https://res.cloudinary.com/dc5clrqtw/image/upload/v1780932970/174254825_29121f25-ddd2-4609-ad16-2c46503f9bee_ugpmuu.jpg"},"military_service":[],"career":[],"birth":{"year":1862,"country":"United States"},"death":{"year":1957,"country":"United States"},"burial":{},"education":[],"slug":"elizabeth-crichton-battelle-1862"},"HD6030":{"id":"HD6030","former_ids":[],"is_placeholder":false,"has_descendants_documented":false,"gender":"male","classification":{"is_thomas_descendant":true,"is_talcott_descendant":false,"is_thomas_spouse":false,"include_in_path_calculation":true,"is_easter_egg":false,"descent_from_thomas_hooker":true,"descent_from_john_talcott":false,"generation_from_thomas":10},"notable":{"is_notable":false,"notable_category":[]},"parents":{"father_id":"I01627","mother_id":"HD6027"},"number_of_marriages":2,"marriages":[{"spouse_id":"I01628","children_ids":["HD6031"],"marriage_number":1},{"spouse_id":"I01629","children_ids":[],"marriage_number":2}],"tags":[],"narrative_blocks":[{"category":"legacy","header":"He gave Litchfield its library building","body":"Vanderpoel offered to erect a building at South and East Streets to house the town library and historical society, free to the people of Litchfield. He died in 1901 while it was under construction, and his mother saw it finished.","number":1},{"category":"family","header":"He named the building for his grandmother","body":"The structure was dedicated as the Noyes Memorial Building in honor of his grandmother, Julia Tallmadge Noyes. A bronze plaque placed by his mother marks his memory beneath its Palladian window.","number":2}],"sources":[],"institutions":[],"landmarks":[{"landmark_id":"LM132","landmark_blurb":"The 1901 Litchfield library building tied to the Noyes and Vanderpoel families."}],"artworks":[],"research_tags":[],"cross_connections":[],"quotes":[],"research_sources":[],"documents":[],"statues":[{"statue_id":"STAT006"}],"bio":{"first_name":"John Arent","last_name":"Vanderpoel","display_name":"John Arent Vanderpoel","gender":"male","bio_blurb":"Donor of the Litchfield library building, 1901"},"military_service":[],"career":[],"birth":{"year":1866,"country":"United States"},"death":{"year":1901,"country":"United States"},"burial":{"cemetery_id":"CEM749"},"education":[],"slug":"john-arent-vanderpoel-1866"},"HD6031":{"id":"HD6031","former_ids":[],"is_placeholder":false,"has_descendants_documented":false,"gender":"male","classification":{"is_thomas_descendant":true,"is_talcott_descendant":false,"is_thomas_spouse":false,"include_in_path_calculation":true,"is_easter_egg":false,"descent_from_thomas_hooker":true,"descent_from_john_talcott":false,"generation_from_thomas":11},"notable":{"is_notable":false,"notable_category":[]},"parents":{"father_id":"HD6030","mother_id":"I01628"},"number_of_marriages":1,"marriages":[{"spouse_id":"I01630","children_ids":["HD6032","HD6033"],"marriage_number":1}],"tags":[],"narrative_blocks":[],"sources":[],"institutions":[],"landmarks":[],"artworks":[],"research_tags":[],"cross_connections":[],"quotes":[],"research_sources":[],"documents":[],"statues":[],"bio":{"first_name":"Floyd Lewis","last_name":"Vanderpoel","display_name":"Floyd Lewis Vanderpoel","gender":"male","photo_url":"https://res.cloudinary.com/dc5clrqtw/image/upload/v1780933061/195817094_61a479fc-71c1-4465-b0c3-f0aadb1b8c8c-resized_h2eu1s.jpg"},"military_service":[],"career":[],"birth":{"year":1891,"country":"United States","city":"New York","state":"New York"},"death":{"year":1948,"country":"United States","state":"Connecticut"},"burial":{"cemetery_id":"CEM749"},"education":[],"slug":"floyd-lewis-vanderpoel-1891"},"I01630":{"id":"I01630","former_ids":[],"is_placeholder":false,"has_descendants_documented":false,"gender":"male","classification":{"is_thomas_descendant":false,"is_talcott_descendant":false,"is_thomas_spouse":false,"include_in_path_calculation":false,"is_easter_egg":false},"notable":{"is_notable":false,"notable_category":[]},"parents":{},"number_of_marriages":1,"marriages":[{"spouse_id":"HD6031","children_ids":["HD6032","HD6033"],"marriage_number":1}],"tags":[],"narrative_blocks":[],"sources":[],"institutions":[],"landmarks":[],"artworks":[],"research_tags":[],"cross_connections":[],"quotes":[],"research_sources":[],"documents":[],"statues":[],"bio":{"first_name":"Jane Chester","last_name":"Cunningham","display_name":"Jane Chester Cunningham Vanderpoel","gender":"female","married_names":["Vanderpoel"],"maiden_name":"Cunningham"},"military_service":[],"career":[],"birth":{"year":1896,"country":"United States"},"death":{"year":1968,"country":"United States"},"burial":{"cemetery_id":"CEM749"},"education":[],"slug":"jane-chester-cunningham-1896"},"HD6032":{"id":"HD6032","former_ids":[],"is_placeholder":false,"has_descendants_documented":false,"gender":"male","classification":{"is_thomas_descendant":true,"is_talcott_descendant":false,"is_thomas_spouse":false,"include_in_path_calculation":true,"is_easter_egg":false,"descent_from_thomas_hooker":true,"descent_from_john_talcott":false,"generation_from_thomas":12},"notable":{"is_notable":false,"notable_category":[]},"parents":{"father_id":"HD6031","mother_id":"I01630"},"number_of_marriages":1,"marriages":[{"spouse_id":"I01631","children_ids":["HD6034"],"marriage_number":1}],"tags":["wwii","air_force"],"narrative_blocks":[{"category":"military","header":"He commanded a bomber squadron in the Pacific","body":"An MIT-trained engineer, Vanderpoel flew as commanding officer of the 424th Bomb Squadron in the Pacific during the Second World War. He retired from the Air Force as a lieutenant colonel in 1967.","number":1},{"category":"career","header":"He built wheelchairs for athletes","body":"After the service Vanderpoel partnered with the wheelchair athlete Bob Hall to manufacture sport wheelchairs. A lifelong cyclist, he logged over two hundred thousand miles and rode antique high-wheel bicycles.","number":2}],"sources":[],"institutions":[],"landmarks":[],"artworks":[],"research_tags":[],"cross_connections":[],"quotes":[],"research_sources":[],"documents":[],"statues":[],"bio":{"first_name":"John Arent","last_name":"Vanderpoel","display_name":"John Arent Vanderpoel","gender":"male","bio_blurb":"WWII bomber commander; MIT engineer","photo_url":"https://res.cloudinary.com/dc5clrqtw/image/upload/v1780933368/lg_2_iepwf4.jpg"},"military_service":[{"conflict":"World War II","allegiance":"United States","unit":"424th Bomb Squadron, U.S. Army Air Forces","rank":"Lieutenant Colonel","notes":"Commanding officer of a B-24 squadron in the Pacific theater; retired from the U.S. Air Force in 1967."}],"career":[],"birth":{"year":1918,"country":"United States","city":"New York","state":"New York"},"death":{"year":2008,"country":"United States"},"burial":{"cemetery_id":"CEM749"},"education":[],"slug":"john-arent-vanderpoel-1918"},"HD6033":{"id":"HD6033","former_ids":[],"is_placeholder":false,"has_descendants_documented":false,"gender":"male","classification":{"is_thomas_descendant":true,"is_talcott_descendant":false,"is_thomas_spouse":false,"include_in_path_calculation":true,"is_easter_egg":false,"descent_from_thomas_hooker":true,"descent_from_john_talcott":false,"generation_from_thomas":12},"notable":{"is_notable":false,"notable_category":[]},"parents":{"father_id":"HD6031","mother_id":"I01630"},"marriages":[],"tags":[],"narrative_blocks":[],"sources":[],"institutions":[],"landmarks":[],"artworks":[],"research_tags":[],"cross_connections":[],"quotes":[],"research_sources":[],"documents":[],"statues":[],"bio":{"first_name":"Eric","last_name":"Vanderpoel","display_name":"Eric Vanderpoel","gender":"male"},"military_service":[],"career":[],"birth":{"year":1921,"country":"United States"},"death":{"year":1940,"country":"United States"},"burial":{},"education":[],"slug":"eric-vanderpoel-1921"}},"burialCemetery":null,"institutionsById":{},"crossConnections":[]}