{"person":{"id":"I01129","classification":{"include_in_path_calculation":false,"descent_from_thomas_hooker":false,"descent_from_john_talcott":false,"is_thomas_descendant":false,"is_talcott_descendant":false,"is_easter_egg":false},"bio":{"display_name":"Francis Waite Corey","first_name":"Francis","middle_name":"Waite","last_name":"Corey","married_names":[]},"gender":"male","birth":{},"death":{},"parents":{},"number_of_marriages":1,"marriages":[{"marriage_number":1,"spouse_id":"H04359","date_year":1875,"date_month":11,"date_day":3,"children_ids":[]}],"tags":[],"notable":{"is_notable":false,"notable_category":[]},"cross_connections":[],"narrative_blocks":[],"slug":"francis-corey"},"neighborhood":{"focus":{"id":"I01129","slug":"francis-corey","n":"Francis Waite Corey","by":null,"dy":null,"sx":"m","hd":false,"td":false,"ee":false,"g":null},"spouses":[{"order":1,"spouse":{"id":"H04359","slug":"caroline-hooker-1847","n":"Caroline Christine Hooker","by":1847,"dy":null,"sx":"f","hd":true,"td":false,"ee":false,"g":9},"year":1875,"children":[]}],"parents":{},"grandparents":{"paternal":{},"maternal":{}},"grandchildren":[],"siblings_count":0},"context":{"I01129":{"id":"I01129","classification":{"include_in_path_calculation":false,"descent_from_thomas_hooker":false,"descent_from_john_talcott":false,"is_thomas_descendant":false,"is_talcott_descendant":false,"is_easter_egg":false},"bio":{"display_name":"Francis Waite Corey","first_name":"Francis","middle_name":"Waite","last_name":"Corey","married_names":[]},"gender":"male","birth":{},"death":{},"parents":{},"number_of_marriages":1,"marriages":[{"marriage_number":1,"spouse_id":"H04359","date_year":1875,"date_month":11,"date_day":3,"children_ids":[]}],"tags":[],"notable":{"is_notable":false,"notable_category":[]},"cross_connections":[],"narrative_blocks":[],"slug":"francis-corey"},"H04359":{"id":"H04359","classification":{"include_in_path_calculation":true,"descent_from_thomas_hooker":true,"descent_from_john_talcott":false,"is_thomas_descendant":true,"is_talcott_descendant":false,"generation_from_thomas":9,"is_easter_egg":false},"bio":{"display_name":"Caroline Christine Hooker","first_name":"Caroline","middle_name":"Christine","last_name":"Hooker","maiden_name":"Hooker","married_names":[]},"gender":"female","birth":{"year":1847,"month":5,"day":24,"city":"Hartford","state":"Connecticut","country":"United States"},"death":{},"parents":{"father_id":"H02754","mother_id":"I01126"},"number_of_marriages":1,"marriages":[{"marriage_number":1,"spouse_id":"I01129","date_year":1875,"date_month":11,"date_day":3,"children_ids":[]}],"tags":[],"notable":{"is_notable":false,"notable_category":[]},"cross_connections":[],"narrative_blocks":[],"slug":"caroline-hooker-1847"}},"burialCemetery":null,"institutionsById":{},"crossConnections":[]}