{"person":{"id":"I01008","former_ids":[],"is_placeholder":false,"has_descendants_documented":false,"bio":{"first_name":"Justin","middle_name":"Lent","last_name":"Bishop","married_names":[],"gender":"male","display_name":"Justin Lent Bishop"},"birth":{},"baptism":{},"death":{},"residence":{"country":"United States"},"burial":{},"classification":{"is_thomas_descendant":false,"is_talcott_descendant":false,"is_thomas_spouse":false,"is_talcott_spouse":false,"include_in_path_calculation":false,"descent_paths_to_thomas":0,"descent_from_thomas_hooker":false,"is_progenitor":false,"is_easter_egg":false},"notable":{"is_notable":false,"notable_category":[]},"parents":{},"number_of_marriages":1,"marriages":[{"marriage_number":1,"spouse_id":"H02405","date_year":1845,"date_month":2,"date_day":27,"location_country":"United States","children_ids":[]}],"education":[],"career":[],"military_service":[],"institutions":[],"landmarks":[],"naming_inspiration":[],"artworks":[],"tags":[],"research_tags":[],"cross_connections":[],"narrative_blocks":[],"quotes":[],"sources":[{"label":"Edward Hooker, Descendants of Rev. Thomas Hooker (1909)","url":"https://archive.org/details/descendantsofrev00hook"}],"research_sources":[],"documents":[],"slug":"justin-bishop"},"neighborhood":{"focus":{"id":"I01008","slug":"justin-bishop","n":"Justin Lent Bishop","by":null,"dy":null,"sx":"u","hd":false,"td":false,"ee":false,"g":null},"spouses":[{"order":1,"spouse":{"id":"H02405","slug":"julia-bishop-1820","n":"Julia Amanda Bishop","by":1820,"dy":null,"sx":"u","hd":true,"td":true,"ee":false,"g":8},"year":1845,"children":[]}],"parents":{},"grandparents":{"paternal":{},"maternal":{}},"grandchildren":[],"siblings_count":0},"context":{"I01008":{"id":"I01008","former_ids":[],"is_placeholder":false,"has_descendants_documented":false,"bio":{"first_name":"Justin","middle_name":"Lent","last_name":"Bishop","married_names":[],"gender":"male","display_name":"Justin Lent Bishop"},"birth":{},"baptism":{},"death":{},"residence":{"country":"United States"},"burial":{},"classification":{"is_thomas_descendant":false,"is_talcott_descendant":false,"is_thomas_spouse":false,"is_talcott_spouse":false,"include_in_path_calculation":false,"descent_paths_to_thomas":0,"descent_from_thomas_hooker":false,"is_progenitor":false,"is_easter_egg":false},"notable":{"is_notable":false,"notable_category":[]},"parents":{},"number_of_marriages":1,"marriages":[{"marriage_number":1,"spouse_id":"H02405","date_year":1845,"date_month":2,"date_day":27,"location_country":"United States","children_ids":[]}],"education":[],"career":[],"military_service":[],"institutions":[],"landmarks":[],"naming_inspiration":[],"artworks":[],"tags":[],"research_tags":[],"cross_connections":[],"narrative_blocks":[],"quotes":[],"sources":[{"label":"Edward Hooker, Descendants of Rev. Thomas Hooker (1909)","url":"https://archive.org/details/descendantsofrev00hook"}],"research_sources":[],"documents":[],"slug":"justin-bishop"},"H02405":{"id":"H02405","former_ids":[],"is_placeholder":false,"has_descendants_documented":false,"bio":{"first_name":"Julia","middle_name":"Amanda","last_name":"Bishop","maiden_name":"Root","married_names":["Bishop"],"gender":"female","display_name":"Julia Amanda Bishop"},"birth":{"year":1820,"month":11,"day":28,"city":"Moscow","state":"New York","country":"United States"},"baptism":{},"death":{},"residence":{"country":"United States"},"burial":{},"classification":{"is_thomas_descendant":true,"is_talcott_descendant":true,"is_thomas_spouse":false,"is_talcott_spouse":false,"generation_from_thomas":8,"generation_from_john_talcott":7,"include_in_path_calculation":true,"descent_paths_to_thomas":1,"descent_from_thomas_hooker":true,"is_progenitor":false,"is_easter_egg":false},"notable":{"is_notable":false,"notable_category":[]},"parents":{"father_id":"H01265","mother_id":"I00990"},"number_of_marriages":1,"marriages":[{"marriage_number":1,"spouse_id":"I01008","date_year":1845,"date_month":2,"date_day":27,"location_country":"United States","children_ids":[]}],"education":[],"career":[],"military_service":[],"institutions":[],"landmarks":[],"naming_inspiration":[],"artworks":[],"tags":[],"research_tags":[],"cross_connections":[],"narrative_blocks":[],"quotes":[],"sources":[{"label":"Edward Hooker, Descendants of Rev. Thomas Hooker (1909)","url":"https://archive.org/details/descendantsofrev00hook"}],"research_sources":[],"documents":[],"slug":"julia-bishop-1820"}},"burialCemetery":null,"institutionsById":{},"crossConnections":[]}