{"person":{"id":"X01325","has_descendants_documented":false,"classification":{"include_in_path_calculation":false,"descent_from_thomas_hooker":false,"descent_from_john_talcott":false,"is_thomas_descendant":false,"is_talcott_descendant":false,"is_easter_egg":false},"tags":[],"sources":[],"gender":"female","number_of_marriages":1,"marriages":[{"marriage_number":1,"spouse_id":"H00644","date_year":1800,"date_month":3,"date_day":10,"location_state":"New York","children_ids":["HD0812"]}],"parents":{},"notable":{"is_notable":false,"notable_category":[]},"birth":{},"death":{},"cross_connections":[],"bio":{"display_name":"Mary Trask","first_name":"Mary","maiden_name":"Trask","married_names":[]},"residence":{},"baptism":{},"research_tags":[],"research_sources":[],"documents":[],"naming_inspiration":[],"institutions":[],"landmarks":[],"artworks":[],"quotes":[],"military_service":[],"slug":"mary-trask"},"neighborhood":{"focus":{"id":"X01325","slug":"mary-trask","n":"Mary Trask","by":null,"dy":null,"sx":"f","hd":false,"td":false,"ee":false,"g":null},"spouses":[{"order":1,"spouse":{"id":"H00644","slug":"jared-hooker-1772","n":"Jared Ingersoll Hooker","by":1772,"dy":1843,"sx":"m","hd":true,"td":false,"ee":false,"g":6},"year":1800,"children":[{"id":"HD0812","slug":"edward-hooker-1809","n":"Edward Trask Hooker","by":1809,"dy":1877,"sx":"m","hd":true,"td":false,"ee":false,"g":7}]}],"parents":{},"grandparents":{"paternal":{},"maternal":{}},"grandchildren":[],"siblings_count":0},"context":{"X01325":{"id":"X01325","has_descendants_documented":false,"classification":{"include_in_path_calculation":false,"descent_from_thomas_hooker":false,"descent_from_john_talcott":false,"is_thomas_descendant":false,"is_talcott_descendant":false,"is_easter_egg":false},"tags":[],"sources":[],"gender":"female","number_of_marriages":1,"marriages":[{"marriage_number":1,"spouse_id":"H00644","date_year":1800,"date_month":3,"date_day":10,"location_state":"New York","children_ids":["HD0812"]}],"parents":{},"notable":{"is_notable":false,"notable_category":[]},"birth":{},"death":{},"cross_connections":[],"bio":{"display_name":"Mary Trask","first_name":"Mary","maiden_name":"Trask","married_names":[]},"residence":{},"baptism":{},"research_tags":[],"research_sources":[],"documents":[],"naming_inspiration":[],"institutions":[],"landmarks":[],"artworks":[],"quotes":[],"military_service":[],"slug":"mary-trask"},"H00644":{"id":"H00644","has_descendants_documented":true,"classification":{"include_in_path_calculation":true,"generation_from_thomas":6,"descent_from_thomas_hooker":true,"descent_from_john_talcott":false,"is_thomas_descendant":true,"is_talcott_descendant":false,"is_easter_egg":false},"birth":{"year":1772,"month":3,"day":12,"city":"Farmington","state":"Connecticut"},"parents":{"father_id":"H00292","mother_id":"I01758"},"tags":["not_yet_fully_entered","named_for_hooker"],"sources":[{"short":"Edward Hooker 1909","page":"Entry 644"}],"death":{"year":1843,"month":1,"day":30,"city":"Sangerfield","state":"New York"},"marriages":[{"children_ids":["HD0812"],"spouse_id":"X01325","marriage_number":1,"date_year":1800,"date_month":3,"date_day":10,"location_state":"New York"}],"gender":"male","number_of_marriages":1,"notable":{"is_notable":false,"notable_category":[]},"cross_connections":[],"bio":{"display_name":"Jared Ingersoll Hooker","first_name":"Jared","last_name":"Hooker","middle_name":"Ingersoll","married_names":[]},"residence":{},"baptism":{},"research_tags":[],"research_sources":[],"documents":[],"naming_inspiration":[],"institutions":[],"landmarks":[],"artworks":[],"quotes":[],"military_service":[],"slug":"jared-hooker-1772"},"HD0812":{"id":"HD0812","has_descendants_documented":true,"classification":{"include_in_path_calculation":true,"generation_from_thomas":7,"descent_from_thomas_hooker":true,"descent_from_john_talcott":false,"is_thomas_descendant":true,"is_talcott_descendant":false,"is_easter_egg":false},"birth":{"year":1809,"month":3,"day":7,"city":"Sangerfield","state":"New York"},"death":{"year":1877,"month":4,"day":24,"city":"Wisconsin Dells","state":"Wisconsin"},"parents":{"father_id":"H00644","mother_research_notes":"Mary Trask Hooker","mother_id":"X01325"},"marriages":[{"spouse_id":"X00132","marriage_number":1,"children_ids":[]}],"tags":["wisconsin_migration"],"sources":[],"gender":"male","number_of_marriages":1,"notable":{"is_notable":false,"notable_category":[]},"cross_connections":[],"bio":{"display_name":"Edward Trask Hooker","first_name":"Edward","last_name":"Hooker","middle_name":"Trask","married_names":[]},"residence":{},"baptism":{},"research_tags":[],"research_sources":[],"documents":[],"naming_inspiration":[],"institutions":[],"landmarks":[],"artworks":[],"quotes":[],"military_service":[],"slug":"edward-hooker-1809"},"X00132":{"id":"X00132","has_descendants_documented":false,"classification":{"include_in_path_calculation":false,"descent_from_thomas_hooker":false,"descent_from_john_talcott":false,"is_thomas_descendant":false,"is_talcott_descendant":false,"is_easter_egg":false},"tags":[],"sources":[],"birth":{"year":1833},"death":{"year":1866,"city":"Columbia County","state":"Wisconsin"},"gender":"female","number_of_marriages":1,"marriages":[{"marriage_number":1,"spouse_id":"HD0812","children_ids":[]}],"parents":{},"notable":{"is_notable":false,"notable_category":[]},"cross_connections":[],"bio":{"display_name":"Almira T Markham","first_name":"Almira","middle_name":"T","maiden_name":"Markham","married_names":[]},"residence":{},"baptism":{},"research_tags":[],"research_sources":[],"documents":[],"naming_inspiration":[],"institutions":[],"landmarks":[],"artworks":[],"quotes":[],"military_service":[],"slug":"almira-markham-1833"}},"burialCemetery":null,"institutionsById":{},"crossConnections":[]}