{"person":{"id":"X02562","former_ids":[],"is_placeholder":true,"has_descendants_documented":false,"bio":{"first_name":"Sally","last_name":"Munger","married_names":[],"gender":"female","display_name":"Sally Munger"},"birth":{},"baptism":{},"death":{},"residence":{},"burial":{},"classification":{"is_thomas_descendant":false,"is_talcott_descendant":false,"is_thomas_spouse":true,"is_talcott_spouse":false,"include_in_path_calculation":false,"descent_paths_to_thomas":0,"descent_from_thomas_hooker":false,"descent_from_john_talcott":false,"is_progenitor":false,"is_easter_egg":false},"notable":{"is_notable":false,"notable_category":[]},"parents":{},"number_of_marriages":1,"marriages":[{"marriage_number":1,"spouse_id":"H02156","date_year":1831,"date_month":4,"date_day":17,"location_country":"United States","end_type":"death_of_spouse","end_year":1873,"children_ids":[]}],"education":[],"career":[],"military_service":[],"institutions":[],"landmarks":[],"naming_inspiration":[],"artworks":[],"tags":[],"research_tags":["needs_research","not_yet_fully_entered"],"cross_connections":[],"narrative_blocks":[],"quotes":[],"sources":[],"research_sources":[],"documents":[],"slug":"sally-munger-x02562"},"neighborhood":{"focus":{"id":"X02562","slug":"sally-munger-x02562","n":"Sally Munger","by":null,"dy":null,"sx":"u","hd":false,"td":false,"ee":false,"g":null},"spouses":[{"order":1,"spouse":{"id":"H02156","slug":"dickenson-murray-1805","n":"Dickenson Murray","by":1805,"dy":1873,"sx":"u","hd":true,"td":false,"ee":false,"g":7},"year":1831,"children":[]}],"parents":{},"grandparents":{"paternal":{},"maternal":{}},"grandchildren":[],"siblings_count":0},"context":{"X02562":{"id":"X02562","former_ids":[],"is_placeholder":true,"has_descendants_documented":false,"bio":{"first_name":"Sally","last_name":"Munger","married_names":[],"gender":"female","display_name":"Sally Munger"},"birth":{},"baptism":{},"death":{},"residence":{},"burial":{},"classification":{"is_thomas_descendant":false,"is_talcott_descendant":false,"is_thomas_spouse":true,"is_talcott_spouse":false,"include_in_path_calculation":false,"descent_paths_to_thomas":0,"descent_from_thomas_hooker":false,"descent_from_john_talcott":false,"is_progenitor":false,"is_easter_egg":false},"notable":{"is_notable":false,"notable_category":[]},"parents":{},"number_of_marriages":1,"marriages":[{"marriage_number":1,"spouse_id":"H02156","date_year":1831,"date_month":4,"date_day":17,"location_country":"United States","end_type":"death_of_spouse","end_year":1873,"children_ids":[]}],"education":[],"career":[],"military_service":[],"institutions":[],"landmarks":[],"naming_inspiration":[],"artworks":[],"tags":[],"research_tags":["needs_research","not_yet_fully_entered"],"cross_connections":[],"narrative_blocks":[],"quotes":[],"sources":[],"research_sources":[],"documents":[],"slug":"sally-munger-x02562"},"H02156":{"id":"H02156","former_ids":[],"is_placeholder":false,"has_descendants_documented":false,"bio":{"first_name":"Dickenson","last_name":"Murray","married_names":[],"gender":"male","display_name":"Dickenson Murray"},"birth":{"year":1805,"month":12,"day":2,"city":"East Guilford","county":"New Haven","state":"Connecticut","country":"United States"},"baptism":{},"death":{"year":1873,"month":10,"day":9,"country":"United States"},"residence":{},"burial":{},"classification":{"is_thomas_descendant":true,"is_talcott_descendant":false,"is_thomas_spouse":false,"is_talcott_spouse":false,"generation_from_thomas":7,"include_in_path_calculation":true,"descent_paths_to_thomas":1,"descent_from_thomas_hooker":true,"descent_from_john_talcott":false,"is_progenitor":false,"is_easter_egg":false},"notable":{"is_notable":false,"notable_category":[]},"parents":{"father_id":"X02455","mother_id":"H01044"},"number_of_marriages":1,"marriages":[{"marriage_number":1,"spouse_id":"X02562","date_year":1831,"date_month":4,"date_day":17,"location_country":"United States","end_type":"death","end_year":1873,"children_ids":[]}],"education":[],"career":[],"military_service":[],"institutions":[],"landmarks":[],"naming_inspiration":[{"name_element":"Dickenson","inspired_by_id":"X02452","description":"Given his great-grandmother Mary Dickenson Scranton's surname as a first name — Mary was the mother of Phebe Scranton Norton."}],"artworks":[],"tags":[],"research_tags":[],"cross_connections":[],"narrative_blocks":[],"quotes":[],"sources":[],"research_sources":[],"documents":[],"slug":"dickenson-murray-1805"}},"burialCemetery":null,"institutionsById":{},"crossConnections":[]}