{"person":{"id":"X01413","has_descendants_documented":false,"classification":{"include_in_path_calculation":false,"descent_from_thomas_hooker":false,"descent_from_john_talcott":false,"is_thomas_descendant":false,"is_talcott_descendant":false,"is_easter_egg":false},"tags":[],"sources":[],"gender":"male","number_of_marriages":4,"marriages":[{"marriage_number":1,"spouse_id":"HD0938","children_ids":[]},{"marriage_number":2,"spouse_id":"HD1313","children_ids":[]},{"marriage_number":3,"spouse_id":"HD1754","children_ids":[]},{"marriage_number":4,"spouse_id":"HD1886","children_ids":[]}],"parents":{},"notable":{"is_notable":false,"notable_category":[]},"birth":{},"death":{},"cross_connections":[],"bio":{"display_name":"Smith","first_name":"Smith","married_names":[]},"residence":{},"baptism":{},"research_tags":[],"research_sources":[],"documents":[],"naming_inspiration":[],"institutions":[],"landmarks":[],"artworks":[],"quotes":[],"military_service":[],"slug":"smith-x01413"},"neighborhood":{"focus":{"id":"X01413","slug":"smith-x01413","n":"Smith","by":null,"dy":null,"sx":"m","hd":false,"td":false,"ee":false,"g":null},"spouses":[{"order":1,"spouse":{"id":"HD0938","slug":"maria-hine-1802","n":"Maria Hine","by":1802,"dy":null,"sx":"f","hd":true,"td":false,"ee":false,"g":7},"year":null,"children":[]},{"order":2,"spouse":{"id":"HD1313","slug":"mary-smith-1840","n":"Mary A. Pierpont Smith","by":1840,"dy":1903,"sx":"f","hd":true,"td":false,"ee":false,"g":7},"year":null,"children":[]},{"order":3,"spouse":{"id":"HD1754","slug":"lucretia-todd-1823","n":"Lucretia Ingersoll Todd","by":1823,"dy":1899,"sx":"u","hd":true,"td":false,"ee":false,"g":8},"year":null,"children":[]},{"order":4,"spouse":{"id":"HD1886","slug":"louisa-smith-1840","n":"Louisa Perry Ingersoll Smith","by":1840,"dy":1897,"sx":"f","hd":true,"td":false,"ee":false,"g":8},"year":null,"children":[]}],"parents":{},"grandparents":{"paternal":{},"maternal":{}},"grandchildren":[],"siblings_count":0},"context":{"X01413":{"id":"X01413","has_descendants_documented":false,"classification":{"include_in_path_calculation":false,"descent_from_thomas_hooker":false,"descent_from_john_talcott":false,"is_thomas_descendant":false,"is_talcott_descendant":false,"is_easter_egg":false},"tags":[],"sources":[],"gender":"male","number_of_marriages":4,"marriages":[{"marriage_number":1,"spouse_id":"HD0938","children_ids":[]},{"marriage_number":2,"spouse_id":"HD1313","children_ids":[]},{"marriage_number":3,"spouse_id":"HD1754","children_ids":[]},{"marriage_number":4,"spouse_id":"HD1886","children_ids":[]}],"parents":{},"notable":{"is_notable":false,"notable_category":[]},"birth":{},"death":{},"cross_connections":[],"bio":{"display_name":"Smith","first_name":"Smith","married_names":[]},"residence":{},"baptism":{},"research_tags":[],"research_sources":[],"documents":[],"naming_inspiration":[],"institutions":[],"landmarks":[],"artworks":[],"quotes":[],"military_service":[],"slug":"smith-x01413"},"HD0938":{"id":"HD0938","has_descendants_documented":false,"classification":{"include_in_path_calculation":false,"generation_from_thomas":7,"descent_from_thomas_hooker":true,"descent_from_john_talcott":false,"is_thomas_descendant":true,"is_talcott_descendant":false,"is_easter_egg":false},"parents":{"father_id":"HD0230","mother_id":"X00192"},"tags":[],"sources":[],"birth":{"year":1802},"gender":"female","marriages":[{"spouse_id":"X01413","children_ids":[],"marriage_number":1}],"number_of_marriages":1,"notable":{"is_notable":false,"notable_category":[]},"death":{},"cross_connections":[],"bio":{"display_name":"Maria Hine","first_name":"Maria","maiden_name":"Hine","married_names":[]},"residence":{},"baptism":{},"research_tags":[],"research_sources":[],"documents":[],"naming_inspiration":[],"institutions":[],"landmarks":[],"artworks":[],"quotes":[],"military_service":[],"slug":"maria-hine-1802"},"HD1313":{"id":"HD1313","has_descendants_documented":false,"classification":{"include_in_path_calculation":false,"generation_from_thomas":7,"descent_from_thomas_hooker":true,"descent_from_john_talcott":false,"is_thomas_descendant":true,"is_talcott_descendant":false,"is_easter_egg":false},"parents":{"father_id":"H00836","mother_id":"X00405"},"tags":[],"sources":[],"birth":{"year":1840},"death":{"year":1903},"gender":"female","marriages":[{"spouse_id":"X01413","children_ids":[],"marriage_number":1}],"number_of_marriages":1,"notable":{"is_notable":false,"notable_category":[]},"cross_connections":[],"bio":{"display_name":"Mary A. Pierpont Smith","first_name":"Mary","last_name":"Smith","maiden_name":"Pierpont","middle_name":"A.","married_names":["Smith"]},"residence":{},"baptism":{},"research_tags":[],"research_sources":[],"documents":[],"naming_inspiration":[],"institutions":[],"landmarks":[],"artworks":[],"quotes":[],"military_service":[],"slug":"mary-smith-1840"},"HD1754":{"id":"HD1754","has_descendants_documented":false,"classification":{"include_in_path_calculation":false,"generation_from_thomas":8,"descent_from_thomas_hooker":true,"descent_from_john_talcott":false,"is_thomas_descendant":true,"is_talcott_descendant":false,"is_easter_egg":false},"birth":{"year":1823},"death":{"year":1899},"parents":{"father_id":"X00566","mother_id":"HD1691"},"marriages":[{"spouse_id":"X01413","children_ids":[],"marriage_number":1}],"tags":[],"sources":[],"gender":"unknown","number_of_marriages":1,"notable":{"is_notable":false,"notable_category":[]},"cross_connections":[],"bio":{"display_name":"Lucretia Ingersoll Todd","first_name":"Lucretia","last_name":"Todd","married_names":["Smith"],"middle_name":"Ingersoll"},"residence":{},"baptism":{},"research_tags":[],"research_sources":[],"documents":[],"naming_inspiration":[],"institutions":[],"landmarks":[],"artworks":[],"quotes":[],"military_service":[],"slug":"lucretia-todd-1823"},"HD1886":{"id":"HD1886","has_descendants_documented":false,"classification":{"include_in_path_calculation":false,"generation_from_thomas":8,"descent_from_thomas_hooker":true,"descent_from_john_talcott":false,"is_thomas_descendant":true,"is_talcott_descendant":false,"is_easter_egg":false},"birth":{"year":1840},"death":{"year":1897},"parents":{"father_id":"HD1696","mother_id":"X00607"},"marriages":[{"spouse_id":"X01413","children_ids":[],"marriage_number":1}],"tags":[],"sources":[],"gender":"female","number_of_marriages":1,"notable":{"is_notable":false,"notable_category":[]},"cross_connections":[],"bio":{"display_name":"Louisa Perry Ingersoll Smith","first_name":"Louisa","last_name":"Smith","married_names":["Smith"],"middle_name":"Perry","maiden_name":"Ingersoll"},"residence":{},"baptism":{},"research_tags":[],"research_sources":[],"documents":[],"naming_inspiration":[],"institutions":[],"landmarks":[],"artworks":[],"quotes":[],"military_service":[],"slug":"louisa-smith-1840"}},"burialCemetery":null,"institutionsById":{},"crossConnections":[]}