{"person":{"id":"HD2199","has_descendants_documented":true,"classification":{"include_in_path_calculation":true,"generation_from_thomas":8,"descent_from_thomas_hooker":true,"descent_from_john_talcott":false,"is_thomas_descendant":true,"is_talcott_descendant":false,"is_easter_egg":false},"parents":{"father_id":"HD2186","mother_id":"X00697"},"tags":[],"sources":[],"birth":{"year":1834},"death":{"year":1893},"gender":"male","marriages":[],"notable":{"is_notable":false,"notable_category":[]},"cross_connections":[],"bio":{"display_name":"William Cecil Dwight","first_name":"William","last_name":"Dwight","middle_name":"Cecil","married_names":[]},"residence":{},"baptism":{},"research_tags":[],"research_sources":[],"documents":[],"naming_inspiration":[],"institutions":[],"landmarks":[],"artworks":[],"quotes":[],"military_service":[],"slug":"william-dwight-1834"},"neighborhood":{"focus":{"id":"HD2199","slug":"william-dwight-1834","n":"William Cecil Dwight","by":1834,"dy":1893,"sx":"m","hd":true,"td":false,"ee":false,"g":8},"spouses":[],"parents":{"father":{"id":"HD2186","slug":"william-dwight-1799","n":"William Cecil Dwight","by":1799,"dy":1853,"sx":"m","hd":true,"td":false,"ee":false,"g":7},"mother":{"id":"X00697","slug":"laura-talbot-1814","n":"Laura Richmond Talbot","by":1814,"dy":1866,"sx":"f","hd":false,"td":false,"ee":false,"g":null}},"grandparents":{"paternal":{"father":{"id":"H00925","slug":"cecil-dwight-1774","n":"Cecil Dwight","by":1774,"dy":1839,"sx":"m","hd":true,"td":false,"ee":false,"g":6},"mother":{"id":"X00672","slug":"mary-clap","n":"Mary Clap","by":null,"dy":null,"sx":"f","hd":false,"td":false,"ee":false,"g":null}},"maternal":{}},"grandchildren":[],"siblings_count":8},"context":{"HD2199":{"id":"HD2199","has_descendants_documented":true,"classification":{"include_in_path_calculation":true,"generation_from_thomas":8,"descent_from_thomas_hooker":true,"descent_from_john_talcott":false,"is_thomas_descendant":true,"is_talcott_descendant":false,"is_easter_egg":false},"parents":{"father_id":"HD2186","mother_id":"X00697"},"tags":[],"sources":[],"birth":{"year":1834},"death":{"year":1893},"gender":"male","marriages":[],"notable":{"is_notable":false,"notable_category":[]},"cross_connections":[],"bio":{"display_name":"William Cecil Dwight","first_name":"William","last_name":"Dwight","middle_name":"Cecil","married_names":[]},"residence":{},"baptism":{},"research_tags":[],"research_sources":[],"documents":[],"naming_inspiration":[],"institutions":[],"landmarks":[],"artworks":[],"quotes":[],"military_service":[],"slug":"william-dwight-1834"},"HD2186":{"id":"HD2186","has_descendants_documented":true,"classification":{"include_in_path_calculation":true,"generation_from_thomas":7,"descent_from_thomas_hooker":true,"descent_from_john_talcott":false,"is_thomas_descendant":true,"is_talcott_descendant":false,"is_easter_egg":false},"parents":{"father_id":"H00925","mother_id":"X00672"},"tags":["physician"],"sources":[],"birth":{"year":1799,"month":3,"day":4,"city":"Northampton","state":"Massachusetts"},"death":{"year":1853,"month":5,"day":6,"city":"Norwalk","state":"Connecticut"},"marriages":[{"spouse_id":"X00696","children_ids":["HD2197","HD2198"],"marriage_number":1,"date_year":1826,"date_month":8,"date_day":18},{"spouse_id":"X00697","children_ids":["HD2199","HD2200","HD2201","HD2202","HD2203","HD2204","HD2205"],"marriage_number":2,"date_year":1833,"date_month":6,"date_day":24,"location_city":"Rochester","location_state":"New York"}],"gender":"male","number_of_marriages":2,"notable":{"is_notable":false,"notable_category":[]},"cross_connections":[],"bio":{"display_name":"William Cecil Dwight","first_name":"William","last_name":"Dwight","middle_name":"Cecil","married_names":[]},"residence":{},"baptism":{},"research_tags":[],"research_sources":[],"documents":[],"naming_inspiration":[],"institutions":[],"landmarks":[],"artworks":[],"quotes":[],"military_service":[],"slug":"william-dwight-1799"},"X00697":{"id":"X00697","has_descendants_documented":false,"classification":{"include_in_path_calculation":false,"descent_from_thomas_hooker":false,"descent_from_john_talcott":false,"is_thomas_descendant":false,"is_talcott_descendant":false,"is_easter_egg":false},"tags":[],"sources":[],"birth":{"year":1814,"month":9,"day":3},"death":{"year":1866},"gender":"female","number_of_marriages":1,"marriages":[{"marriage_number":1,"spouse_id":"HD2186","date_year":1833,"date_month":6,"date_day":24,"location_city":"Rochester","location_state":"New York","children_ids":["HD2199","HD2200","HD2201","HD2202","HD2203","HD2204","HD2205"]}],"parents":{},"notable":{"is_notable":false,"notable_category":[]},"cross_connections":[],"bio":{"display_name":"Laura Richmond Talbot","first_name":"Laura","middle_name":"Richmond","maiden_name":"Talbot","married_names":[]},"residence":{},"baptism":{},"research_tags":[],"research_sources":[],"documents":[],"naming_inspiration":[],"institutions":[],"landmarks":[],"artworks":[],"quotes":[],"military_service":[],"slug":"laura-talbot-1814"},"H00925":{"id":"H00925","has_descendants_documented":true,"classification":{"include_in_path_calculation":false,"generation_from_thomas":6,"descent_from_thomas_hooker":true,"descent_from_john_talcott":false,"is_thomas_descendant":true,"is_talcott_descendant":false,"is_easter_egg":false},"birth":{"year":1774},"death":{"year":1839},"parents":{"father_id":"X00635","mother_id":"H00379"},"marriages":[{"spouse_id":"X00672","children_ids":["HD2186","HD2187","HD2188","HD2189","HD2190","HD2191","HD2192","HD2193","HD2194","HD2195","HD2196"],"marriage_number":1,"date_year":1798,"date_month":6}],"tags":[],"sources":[{"short":"Edward Hooker 1909","entry":"925"}],"gender":"male","number_of_marriages":1,"notable":{"is_notable":false,"notable_category":[]},"cross_connections":[],"bio":{"display_name":"Cecil Dwight","first_name":"Cecil","last_name":"Dwight","married_names":[]},"residence":{},"baptism":{},"research_tags":[],"research_sources":[],"documents":[],"naming_inspiration":[],"institutions":[],"landmarks":[],"artworks":[],"quotes":[],"military_service":[],"slug":"cecil-dwight-1774"},"X00672":{"id":"X00672","has_descendants_documented":false,"classification":{"include_in_path_calculation":false,"descent_from_thomas_hooker":false,"descent_from_john_talcott":false,"is_thomas_descendant":false,"is_talcott_descendant":false,"is_easter_egg":false},"tags":[],"sources":[],"gender":"female","number_of_marriages":1,"marriages":[{"marriage_number":1,"spouse_id":"H00925","date_year":1798,"date_month":6,"children_ids":["HD2186","HD2187","HD2188","HD2189","HD2190","HD2191","HD2192","HD2193","HD2194","HD2195","HD2196"]}],"parents":{},"notable":{"is_notable":false,"notable_category":[]},"birth":{},"death":{},"cross_connections":[],"bio":{"display_name":"Mary Clap","first_name":"Mary","maiden_name":"Clap","married_names":[]},"residence":{},"baptism":{},"research_tags":[],"research_sources":[],"documents":[],"naming_inspiration":[],"institutions":[],"landmarks":[],"artworks":[],"quotes":[],"military_service":[],"slug":"mary-clap"}},"burialCemetery":null,"institutionsById":{},"crossConnections":[]}